[
  {
    "question": "Largest planet?",
    "options": ["Earth", "Jupiter", "Saturn", "Mars"],
    "answer": "Jupiter"
  },
  {
    "question": "Heaviest metal?",
    "options": ["Iron", "Lead", "Osmium", "Gold"],
    "answer": "Osmium"
  },
  {
    "question": "Smallest bone?",
    "options": ["Femur", "Stapes", "Tibia", "Ulna"],
    "answer": "Stapes"
  },
  {
    "question": "Tallest animal?",
    "options": ["Elephant", "Giraffe", "Bear", "Ostrich"],
    "answer": "Giraffe"
  },
  {
    "question": "Most spoken language?",
    "options": ["English", "Hindi", "Mandarin", "Spanish"],
    "answer": "Mandarin"
  },
  {
    "question": "First U.S. president?",
    "options": ["Lincoln", "Adams", "Washington", "Jefferson"],
    "answer": "Washington"
  },
  {
    "question": "Longest river?",
    "options": ["Amazon", "Nile", "Yangtze", "Mississippi"],
    "answer": "Nile"
  },
  {
    "question": "Capital of France?",
    "options": ["Paris", "Rome", "Berlin", "Madrid"],
    "answer": "Paris"
  },
  {
    "question": "Fastest land animal?",
    "options": ["Lion", "Cheetah", "Horse", "Gazelle"],
    "answer": "Cheetah"
  },
  {
    "question": "Hardest natural substance?",
    "options": ["Steel", "Gold", "Diamond", "Quartz"],
    "answer": "Diamond"
  },
  {
    "question": "Which gas do plants absorb?",
    "options": ["Oxygen", "Carbon Dioxide", "Hydrogen", "Nitrogen"],
    "answer": "Carbon Dioxide"
  },
  {
    "question": "How many continents are there?",
    "options": ["5", "6", "7", "8"],
    "answer": "7"
  },
  {
    "question": "Hottest planet in the solar system?",
    "options": ["Mercury", "Venus", "Mars", "Jupiter"],
    "answer": "Venus"
  },
  {
    "question": "Chemical symbol for water?",
    "options": ["O2", "H2O", "CO2", "HO2"],
    "answer": "H2O"
  },
  {
    "question": "Which country invented pizza?",
    "options": ["France", "Greece", "Italy", "USA"],
    "answer": "Italy"
  },
  {
    "question": "Largest mammal?",
    "options": ["Elephant", "Blue Whale", "Hippopotamus", "Giraffe"],
    "answer": "Blue Whale"
  },
  {
    "question": "Which ocean is the deepest?",
    "options": ["Atlantic", "Indian", "Arctic", "Pacific"],
    "answer": "Pacific"
  },
  {
    "question": "What is the boiling point of water in Celsius?",
    "options": ["90", "100", "120", "80"],
    "answer": "100"
  },
  {
    "question": "Which planet is known as the Red Planet?",
    "options": ["Earth", "Venus", "Mars", "Jupiter"],
    "answer": "Mars"
  },
  {
    "question": "Currency of Japan?",
    "options": ["Yen", "Won", "Dollar", "Euro"],
    "answer": "Yen"
  },
  {
    "question": "Number of planets in the solar system?",
    "options": ["7", "8", "9", "10"],
    "answer": "8"
  },
  {
    "question": "Largest desert in the world?",
    "options": ["Sahara", "Antarctica", "Gobi", "Kalahari"],
    "answer": "Antarctica"
  },
  {
    "question": "Which organ pumps blood?",
    "options": ["Brain", "Lungs", "Liver", "Heart"],
    "answer": "Heart"
  },
  {
    "question": "Most abundant gas in Earth's atmosphere?",
    "options": ["Oxygen", "Carbon Dioxide", "Nitrogen", "Hydrogen"],
    "answer": "Nitrogen"
  },
  {
    "question": "Who wrote 'Hamlet'?",
    "options": ["Charles Dickens", "Jane Austen", "Shakespeare", "Mark Twain"],
    "answer": "Shakespeare"
  },
  {
    "question": "How many legs does a spider have?",
    "options": ["6", "8", "10", "12"],
    "answer": "8"
  },
  {
    "question": "Which blood type is universal donor?",
    "options": ["A", "B", "O-", "AB+"],
    "answer": "O-"
  },
  {
    "question": "Which animal is known for changing colors?",
    "options": ["Chameleon", "Frog", "Octopus", "Caterpillar"],
    "answer": "Chameleon"
  },
  {
    "question": "Which country has the most population?",
    "options": ["India", "USA", "China", "Russia"],
    "answer": "India"
  },
  {
    "question": "How many days in a leap year?",
    "options": ["365", "366", "364", "360"],
    "answer": "366"
  },
  {
    "question": "What is the main language in Brazil?",
    "options": ["Spanish", "Portuguese", "English", "French"],
    "answer": "Portuguese"
  },
  {
    "question": "Which planet has rings?",
    "options": ["Earth", "Mars", "Saturn", "Venus"],
    "answer": "Saturn"
  },
  {
    "question": "Largest internal organ?",
    "options": ["Liver", "Heart", "Lungs", "Kidney"],
    "answer": "Liver"
  },
  {
    "question": "How many teeth does an adult human have?",
    "options": ["28", "30", "32", "36"],
    "answer": "32"
  },
  {
    "question": "How many bones in the adult human body?",
    "options": ["206", "201", "198", "210"],
    "answer": "206"
  },
  {
    "question": "Which country is famous for tulips?",
    "options": ["France", "Netherlands", "Italy", "Belgium"],
    "answer": "Netherlands"
  },
  {
    "question": "What is the capital of Australia?",
    "options": ["Sydney", "Melbourne", "Canberra", "Perth"],
    "answer": "Canberra"
  },
  {
    "question": "Which instrument has black and white keys?",
    "options": ["Guitar", "Violin", "Piano", "Drums"],
    "answer": "Piano"
  },
  {
    "question": "Which planet is closest to the Sun?",
    "options": ["Mercury", "Venus", "Mars", "Earth"],
    "answer": "Mercury"
  },
  {
    "question": "Which animal lays the largest eggs?",
    "options": ["Chicken", "Ostrich", "Duck", "Eagle"],
    "answer": "Ostrich"
  },
  {
    "question": "Which country is the Eiffel Tower in?",
    "options": ["Germany", "Italy", "France", "Spain"],
    "answer": "France"
  },
  {
    "question": "Which bird is known for mimicking sounds?",
    "options": ["Parrot", "Crow", "Eagle", "Owl"],
    "answer": "Parrot"
  },
  {
    "question": "In which sport is the term 'love' used?",
    "options": ["Football", "Tennis", "Cricket", "Basketball"],
    "answer": "Tennis"
  },
  {
    "question": "Which month has 28 or 29 days?",
    "options": ["February", "April", "June", "November"],
    "answer": "February"
  },
  {
    "question": "Which planet is known for its storms?",
    "options": ["Earth", "Saturn", "Jupiter", "Uranus"],
    "answer": "Jupiter"
  },
  {
    "question": "Which element is needed for breathing?",
    "options": ["Carbon", "Oxygen", "Hydrogen", "Helium"],
    "answer": "Oxygen"
  },
  {
    "question": "What is the largest organ in the human body?",
    "options": ["Heart", "Liver", "Skin", "Brain"],
    "answer": "Skin"
  },
  {
    "question": "Which continent is Egypt in?",
    "options": ["Asia", "Europe", "Africa", "Australia"],
    "answer": "Africa"
  },
  {
    "question": "Which color is made by mixing red and blue?",
    "options": ["Purple", "Green", "Orange", "Pink"],
    "answer": "Purple"
  },
  {
    "question": "Which animal is the symbol of peace?",
    "options": ["Dove", "Eagle", "Lion", "Peacock"],
    "answer": "Dove"
  },
  {
    "question": "What is the tallest mountain in the world?",
    "options": ["K2", "Everest", "Kilimanjaro", "Makalu"],
    "answer": "Everest"
  },
  {
    "question": "What is the capital of Canada?",
    "options": ["Toronto", "Vancouver", "Ottawa", "Montreal"],
    "answer": "Ottawa"
  },
  {
    "question": "What is the main ingredient in bread?",
    "options": ["Rice", "Flour", "Corn", "Barley"],
    "answer": "Flour"
  },
  {
    "question": "Who painted the Mona Lisa?",
    "options": ["Michelangelo", "Da Vinci", "Van Gogh", "Picasso"],
    "answer": "Da Vinci"
  },
  {
    "question": "What is the chemical symbol for gold?",
    "options": ["Gd", "Au", "Ag", "Go"],
    "answer": "Au"
  },
  {
    "question": "How many hearts does an octopus have?",
    "options": ["1", "2", "3", "4"],
    "answer": "3"
  },
  {
    "question": "Which country hosted the 2016 Summer Olympics?",
    "options": ["Japan", "Brazil", "USA", "UK"],
    "answer": "Brazil"
  },
  {
    "question": "Which animal is known as the king of the jungle?",
    "options": ["Tiger", "Lion", "Elephant", "Leopard"],
    "answer": "Lion"
  },
  {
    "question": "What does 'www' stand for in a website address?",
    "options": ["World Wide Web", "Web World Wide", "Wide Web World", "World Web Wide"],
    "answer": "World Wide Web"
  },
  {
    "question": "Which continent has the most countries?",
    "options": ["Asia", "Europe", "Africa", "South America"],
    "answer": "Africa"
  },
  {
    "question": "Which country is shaped like a boot?",
    "options": ["Portugal", "Spain", "Italy", "Greece"],
    "answer": "Italy"
  },
  {
    "question": "Which musical instrument has six strings?",
    "options": ["Guitar", "Violin", "Piano", "Drum"],
    "answer": "Guitar"
  },
  {
    "question": "How many players in a soccer team on the field?",
    "options": ["9", "10", "11", "12"],
    "answer": "11"
  },
  {
    "question": "What is the smallest prime number?",
    "options": ["0", "1", "2", "3"],
    "answer": "2"
  },
  {
    "question": "Which natural disaster is measured with the Richter scale?",
    "options": ["Tornado", "Hurricane", "Earthquake", "Flood"],
    "answer": "Earthquake"
  },
  {
    "question": "What is the hardest rock?",
    "options": ["Granite", "Obsidian", "Marble", "Diamond"],
    "answer": "Diamond"
  },
  {
    "question": "Which is the largest island in the world?",
    "options": ["Greenland", "Australia", "New Guinea", "Madagascar"],
    "answer": "Greenland"
  },
  {
    "question": "What do bees collect and use to make honey?",
    "options": ["Water", "Pollen", "Nectar", "Sap"],
    "answer": "Nectar"
  },
  {
    "question": "Which color is a mix of blue and yellow?",
    "options": ["Green", "Purple", "Orange", "Brown"],
    "answer": "Green"
  },
  {
    "question": "Who discovered gravity?",
    "options": ["Einstein", "Newton", "Galileo", "Darwin"],
    "answer": "Newton"
  },
  {
    "question": "What is a baby cat called?",
    "options": ["Puppy", "Cub", "Kitten", "Calf"],
    "answer": "Kitten"
  },
  {
    "question": "Which part of the plant conducts photosynthesis?",
    "options": ["Root", "Stem", "Flower", "Leaf"],
    "answer": "Leaf"
  },
  {
    "question": "What is the name of the fairy in Peter Pan?",
    "options": ["Wendy", "Tinker Bell", "Pixie", "Bella"],
    "answer": "Tinker Bell"
  },
  {
    "question": "What is the name of our galaxy?",
    "options": ["Andromeda", "Milky Way", "Orion", "Pegasus"],
    "answer": "Milky Way"
  },
  {
    "question": "What is the fastest marine mammal?",
    "options": ["Dolphin", "Orca", "Seal", "Blue Whale"],
    "answer": "Dolphin"
  },
  {
    "question": "What do you call an animal that eats only plants?",
    "options": ["Carnivore", "Omnivore", "Herbivore", "Insectivore"],
    "answer": "Herbivore"
  },
  {
    "question": "Which famous scientist developed the theory of relativity?",
    "options": ["Isaac Newton", "Marie Curie", "Albert Einstein", "Niels Bohr"],
    "answer": "Albert Einstein"
  },
  {
    "question": "How many sides does a hexagon have?",
    "options": ["5", "6", "7", "8"],
    "answer": "6"
  },
  {
    "question": "Which animal is known to have black and white stripes?",
    "options": ["Tiger", "Zebra", "Panda", "Skunk"],
    "answer": "Zebra"
  },
  {
    "question": "Which bird is often associated with delivering babies?",
    "options": ["Swan", "Dove", "Stork", "Owl"],
    "answer": "Stork"
  },
  {
    "question": "What does a thermometer measure?",
    "options": ["Speed", "Pressure", "Humidity", "Temperature"],
    "answer": "Temperature"
  },
  {
    "question": "What is the main gas found in the air we breathe?",
    "options": ["Oxygen", "Nitrogen", "Carbon Dioxide", "Hydrogen"],
    "answer": "Nitrogen"
  },
  {
    "question": "Which country is known as the Land of the Rising Sun?",
    "options": ["China", "Thailand", "Japan", "South Korea"],
    "answer": "Japan"
  },
  {
    "question": "How many colors are there in a rainbow?",
    "options": ["5", "6", "7", "8"],
    "answer": "7"
  },
  {
    "question": "What is the capital of Germany?",
    "options": ["Frankfurt", "Munich", "Berlin", "Hamburg"],
    "answer": "Berlin"
  },
  {
    "question": "Which metal is liquid at room temperature?",
    "options": ["Mercury", "Lead", "Iron", "Aluminum"],
    "answer": "Mercury"
  },
  {
    "question": "Who invented the light bulb?",
    "options": ["Edison", "Tesla", "Newton", "Bell"],
    "answer": "Edison"
  },
  {
    "question": "Which insect produces silk?",
    "options": ["Bee", "Butterfly", "Silkworm", "Ant"],
    "answer": "Silkworm"
  },
  {
    "question": "What is the largest bird?",
    "options": ["Eagle", "Penguin", "Ostrich", "Albatross"],
    "answer": "Ostrich"
  },
  {
    "question": "Which country is the Taj Mahal in?",
    "options": ["Pakistan", "India", "Nepal", "Bangladesh"],
    "answer": "India"
  },
  {
    "question": "Which is the smallest continent?",
    "options": ["Europe", "Australia", "South America", "Antarctica"],
    "answer": "Australia"
  },
  {
    "question": "Which star is closest to Earth?",
    "options": ["Alpha Centauri", "Proxima Centauri", "Sirius", "Sun"],
    "answer": "Sun"
  },
  {
    "question": "How many hours in a day?",
    "options": ["12", "24", "48", "60"],
    "answer": "24"
  },
  {
    "question": "What is the main ingredient in sushi?",
    "options": ["Pasta", "Rice", "Bread", "Corn"],
    "answer": "Rice"
  },
  {
    "question": "What is the tallest building in the world (as of 2024)?",
    "options": ["Shanghai Tower", "Abraj Al-Bait", "Burj Khalifa", "One World Trade Center"],
    "answer": "Burj Khalifa"
  },
  {
    "question": "Which ocean is on the east coast of the United States?",
    "options": ["Pacific", "Indian", "Atlantic", "Arctic"],
    "answer": "Atlantic"
  },
  {
    "question": "Which planet is known for having moons named Phobos and Deimos?",
    "options": ["Earth", "Jupiter", "Mars", "Saturn"],
    "answer": "Mars"
  },
  {
    "question": "Which shape has four equal sides and angles?",
    "options": ["Rectangle", "Triangle", "Square", "Trapezoid"],
    "answer": "Square"
  },
  {
    "question": "What is the largest country by area?",
    "options": ["USA", "China", "Russia", "Canada"],
    "answer": "Russia"
  },
  {
    "question": "Which planet is known as the Morning Star?",
    "options": ["Venus", "Mars", "Mercury", "Jupiter"],
    "answer": "Venus"
  },
  {
    "question": "What is the freezing point of water in Celsius?",
    "options": ["0", "32", "100", "-10"],
    "answer": "0"
  },
  {
    "question": "Which animal is the largest land carnivore?",
    "options": ["Lion", "Polar Bear", "Tiger", "Grizzly Bear"],
    "answer": "Polar Bear"
  },
  {
    "question": "What is the capital of Italy?",
    "options": ["Venice", "Rome", "Milan", "Florence"],
    "answer": "Rome"
  },
  {
    "question": "Which is the longest bone in the human body?",
    "options": ["Femur", "Tibia", "Humerus", "Fibula"],
    "answer": "Femur"
  },
  {
    "question": "Which country is known for maple syrup?",
    "options": ["USA", "Canada", "Russia", "Sweden"],
    "answer": "Canada"
  },
  {
    "question": "What is the largest ocean?",
    "options": ["Atlantic", "Indian", "Pacific", "Arctic"],
    "answer": "Pacific"
  },
  {
    "question": "Which is the largest planet in the solar system?",
    "options": ["Earth", "Jupiter", "Saturn", "Neptune"],
    "answer": "Jupiter"
  },
  {
    "question": "What is the capital of Spain?",
    "options": ["Barcelona", "Madrid", "Seville", "Valencia"],
    "answer": "Madrid"
  },
  {
    "question": "Which animal is known for its trunk?",
    "options": ["Elephant", "Rhino", "Hippo", "Giraffe"],
    "answer": "Elephant"
  },
  {
    "question": "Which is the largest continent?",
    "options": ["Africa", "Asia", "Europe", "North America"],
    "answer": "Asia"
  },
  {
    "question": "What is the chemical symbol for sodium?",
    "options": ["Na", "So", "S", "N"],
    "answer": "Na"
  },
  {
    "question": "Which country is known as the Land Down Under?",
    "options": ["New Zealand", "Australia", "South Africa", "Argentina"],
    "answer": "Australia"
  },
  {
    "question": "What is the main ingredient in guacamole?",
    "options": ["Tomato", "Avocado", "Onion", "Pepper"],
    "answer": "Avocado"
  },
  {
    "question": "Which is the smallest planet in the solar system?",
    "options": ["Mercury", "Mars", "Venus", "Pluto"],
    "answer": "Mercury"
  },
  {
    "question": "What is the capital of Russia?",
    "options": ["Moscow", "St. Petersburg", "Kiev", "Sochi"],
    "answer": "Moscow"
  },
  {
    "question": "Which animal is known for building dams?",
    "options": ["Otter", "Beaver", "Muskrat", "Mole"],
    "answer": "Beaver"
  },
  {
    "question": "What is the largest species of shark?",
    "options": ["Great White", "Hammerhead", "Whale Shark", "Tiger Shark"],
    "answer": "Whale Shark"
  },
  {
    "question": "Which is the largest living bird by height?",
    "options": ["Ostrich", "Emu", "Cassowary", "Rhea"],
    "answer": "Ostrich"
  },
  {
    "question": "What is the capital of China?",
    "options": ["Shanghai", "Beijing", "Guangzhou", "Shenzhen"],
    "answer": "Beijing"
  },
  {
    "question": "Which is the largest species of penguin?",
    "options": ["Emperor", "King", "Adelie", "Gentoo"],
    "answer": "Emperor"
  },
  {
    "question": "What is the main ingredient in hummus?",
    "options": ["Lentils", "Chickpeas", "Beans", "Peas"],
    "answer": "Chickpeas"
  },
  {
    "question": "Which is the largest reptile?",
    "options": ["Komodo Dragon", "Saltwater Crocodile", "Alligator", "Anaconda"],
    "answer": "Saltwater Crocodile"
  },
  {
    "question": "What is the capital of Egypt?",
    "options": ["Cairo", "Alexandria", "Giza", "Luxor"],
    "answer": "Cairo"
  },
  {
    "question": "Which is the largest moon in the solar system?",
    "options": ["Titan", "Ganymede", "Europa", "Callisto"],
    "answer": "Ganymede"
  },
  {
    "question": "What is the main ingredient in miso soup?",
    "options": ["Soybean paste", "Rice", "Seaweed", "Fish"],
    "answer": "Soybean paste"
  },
  {
    "question": "Which is the largest rodent?",
    "options": ["Rat", "Capybara", "Beaver", "Guinea Pig"],
    "answer": "Capybara"
  },
  {
    "question": "What is the capital of Mexico?",
    "options": ["Guadalajara", "Mexico City", "Monterrey", "Cancun"],
    "answer": "Mexico City"
  },
  {
    "question": "Which is the largest carnivorous land animal?",
    "options": ["Lion", "Polar Bear", "Grizzly Bear", "Tiger"],
    "answer": "Polar Bear"
  },
  {
    "question": "What is the main ingredient in tofu?",
    "options": ["Soybeans", "Rice", "Wheat", "Corn"],
    "answer": "Soybeans"
  },
  {
    "question": "Which is the largest living lizard?",
    "options": ["Komodo Dragon", "Monitor Lizard", "Iguana", "Gecko"],
    "answer": "Komodo Dragon"
  },
  {
    "question": "What is the capital of South Korea?",
    "options": ["Busan", "Seoul", "Incheon", "Daegu"],
    "answer": "Seoul"
  },
  {
    "question": "Which is the largest marsupial?",
    "options": ["Kangaroo", "Koala", "Wombat", "Tasmanian Devil"],
    "answer": "Kangaroo"
  },
  {
    "question": "What is the main ingredient in paella?",
    "options": ["Rice", "Pasta", "Potato", "Corn"],
    "answer": "Rice"
  },
  {
    "question": "Which is the largest living amphibian?",
    "options": ["Giant Salamander", "Frog", "Toad", "Newt"],
    "answer": "Giant Salamander"
  },
  {
    "question": "What is the capital of Turkey?",
    "options": ["Istanbul", "Ankara", "Izmir", "Bursa"],
    "answer": "Ankara"
  },
  {
    "question": "Which is the largest living fish?",
    "options": ["Whale Shark", "Great White Shark", "Manta Ray", "Sturgeon"],
    "answer": "Whale Shark"
  },
  {
    "question": "What is the main ingredient in borscht?",
    "options": ["Beetroot", "Potato", "Carrot", "Cabbage"],
    "answer": "Beetroot"
  },
  {
    "question": "Which is the largest living snake?",
    "options": ["Anaconda", "Python", "Cobra", "Viper"],
    "answer": "Anaconda"
  },
  {
    "question": "What is the capital of Argentina?",
    "options": ["Buenos Aires", "Cordoba", "Rosario", "Mendoza"],
    "answer": "Buenos Aires"
  },
  {
    "question": "Which is the largest living turtle?",
    "options": ["Leatherback", "Green", "Loggerhead", "Hawksbill"],
    "answer": "Leatherback"
  },
  {
    "question": "What is the main ingredient in falafel?",
    "options": ["Chickpeas", "Lentils", "Beans", "Peas"],
    "answer": "Chickpeas"
  },
  {
    "question": "Which is the largest living bat?",
    "options": ["Flying Fox", "Vampire Bat", "Fruit Bat", "Little Brown Bat"],
    "answer": "Flying Fox"
  },
  {
    "question": "What is the capital of Thailand?",
    "options": ["Bangkok", "Phuket", "Chiang Mai", "Pattaya"],
    "answer": "Bangkok"
  },
  {
    "question": "Which is the largest living primate?",
    "options": ["Gorilla", "Chimpanzee", "Orangutan", "Baboon"],
    "answer": "Gorilla"
  },
  {
    "question": "What is the main ingredient in risotto?",
    "options": ["Rice", "Pasta", "Barley", "Quinoa"],
    "answer": "Rice"
  },
  {
    "question": "Which is the largest living cat?",
    "options": ["Lion", "Tiger", "Leopard", "Jaguar"],
    "answer": "Tiger"
  },
  {
    "question": "What is the capital of Greece?",
    "options": ["Athens", "Thessaloniki", "Patras", "Heraklion"],
    "answer": "Athens"
  },
  {
    "question": "Which is the largest living deer?",
    "options": ["Moose", "Elk", "Red Deer", "Reindeer"],
    "answer": "Moose"
  },
  {
    "question": "What is the main ingredient in tabbouleh?",
    "options": ["Bulgur", "Rice", "Couscous", "Quinoa"],
    "answer": "Bulgur"
  },
  {
    "question": "Which is the largest living bird by wingspan?",
    "options": ["Albatross", "Eagle", "Condor", "Pelican"],
    "answer": "Albatross"
  },
  {
    "question": "What is the capital of Sweden?",
    "options": ["Stockholm", "Gothenburg", "Malmo", "Uppsala"],
    "answer": "Stockholm"
  },
  {
    "question": "Which is the largest living rodent in North America?",
    "options": ["Beaver", "Muskrat", "Porcupine", "Capybara"],
    "answer": "Beaver"
  },
  {
    "question": "What is the main ingredient in polenta?",
    "options": ["Cornmeal", "Wheat", "Rice", "Oats"],
    "answer": "Cornmeal"
  },
  {
    "question": "Which is the largest living land animal?",
    "options": ["Elephant", "Rhino", "Hippo", "Giraffe"],
    "answer": "Elephant"
  },
  {
    "question": "What is the capital of Norway?",
    "options": ["Oslo", "Bergen", "Trondheim", "Stavanger"],
    "answer": "Oslo"
  },
  {
    "question": "Which is the largest living antelope?",
    "options": ["Eland", "Kudu", "Impala", "Gazelle"],
    "answer": "Eland"
  },
  {
    "question": "What is the main ingredient in gnocchi?",
    "options": ["Potato", "Rice", "Wheat", "Corn"],
    "answer": "Potato"
  },
  {
    "question": "Which is the largest living marsupial in Australia?",
    "options": ["Kangaroo", "Koala", "Wombat", "Wallaby"],
    "answer": "Kangaroo"
  },
  {
    "question": "What is the capital of Portugal?",
    "options": ["Lisbon", "Porto", "Faro", "Coimbra"],
    "answer": "Lisbon"
  },
  {
    "question": "Which is the largest living canid?",
    "options": ["Wolf", "Coyote", "Fox", "Jackal"],
    "answer": "Wolf"
  },
  {
    "question": "What is the main ingredient in couscous?",
    "options": ["Wheat", "Rice", "Corn", "Barley"],
    "answer": "Wheat"
  },
  {
    "question": "Which is the largest living parrot?",
    "options": ["Hyacinth Macaw", "African Grey", "Cockatoo", "Amazon Parrot"],
    "answer": "Hyacinth Macaw"
  },
  {
    "question": "What is the capital of Finland?",
    "options": ["Helsinki", "Turku", "Tampere", "Oulu"],
    "answer": "Helsinki"
  },
  {
    "question": "Which is the largest living penguin species?",
    "options": ["Emperor", "King", "Adelie", "Gentoo"],
    "answer": "Emperor"
  },
  {
    "question": "What is the main ingredient in tempura batter?",
    "options": ["Flour", "Rice", "Cornmeal", "Potato"],
    "answer": "Flour"
  },
  {
    "question": "Which is the largest living owl?",
    "options": ["Eurasian Eagle Owl", "Barn Owl", "Snowy Owl", "Great Horned Owl"],
    "answer": "Eurasian Eagle Owl"
  },
  {
    "question": "What is the capital of Denmark?",
    "options": ["Copenhagen", "Aarhus", "Odense", "Aalborg"],
    "answer": "Copenhagen"
  },
  {
    "question": "Which is the largest living frog?",
    "options": ["Goliath Frog", "Bullfrog", "Tree Frog", "Poison Dart Frog"],
    "answer": "Goliath Frog"
  },
  {
    "question": "What is the main ingredient in ramen?",
    "options": ["Noodles", "Rice", "Tofu", "Seaweed"],
    "answer": "Noodles"
  },
  {
    "question": "Which is the largest living whale?",
    "options": ["Blue Whale", "Humpback Whale", "Fin Whale", "Gray Whale"],
    "answer": "Blue Whale"
  },
  {
    "question": "What is the capital of Poland?",
    "options": ["Warsaw", "Krakow", "Gdansk", "Wroclaw"],
    "answer": "Warsaw"
  },
  {
    "question": "Which is the largest living snake by length?",
    "options": ["Reticulated Python", "Anaconda", "King Cobra", "Boa Constrictor"],
    "answer": "Reticulated Python"
  },
  {
    "question": "What is the main ingredient in moussaka?",
    "options": ["Eggplant", "Potato", "Zucchini", "Tomato"],
    "answer": "Eggplant"
  },
  {
    "question": "Which is the largest living dolphin?",
    "options": ["Orca", "Bottlenose", "Spinner", "Common Dolphin"],
    "answer": "Orca"
  },
  {
    "question": "What is the capital of Hungary?",
    "options": ["Budapest", "Debrecen", "Szeged", "Pecs"],
    "answer": "Budapest"
  },
  {
    "question": "Which is the largest living crab?",
    "options": ["Japanese Spider Crab", "King Crab", "Blue Crab", "Dungeness Crab"],
    "answer": "Japanese Spider Crab"
  },
  {
    "question": "What is the main ingredient in gazpacho?",
    "options": ["Tomato", "Cucumber", "Pepper", "Onion"],
    "answer": "Tomato"
  },
  {
    "question": "Which is the largest living bony fish?",
    "options": ["Ocean Sunfish", "Tuna", "Marlin", "Swordfish"],
    "answer": "Ocean Sunfish"
  },
  {
    "question": "What is the capital of Ireland?",
    "options": ["Dublin", "Cork", "Galway", "Limerick"],
    "answer": "Dublin"
  },
  {
    "question": "Which is the largest living rodent in South America?",
    "options": ["Capybara", "Guinea Pig", "Chinchilla", "Agouti"],
    "answer": "Capybara"
  },
  {
    "question": "What is the main ingredient in kimchi?",
    "options": ["Cabbage", "Radish", "Carrot", "Spinach"],
    "answer": "Cabbage"
  },
  {
    "question": "Which is the largest living eagle?",
    "options": ["Harpy Eagle", "Bald Eagle", "Golden Eagle", "Steller's Sea Eagle"],
    "answer": "Steller's Sea Eagle"
  },
  {
    "question": "What is the capital of Switzerland?",
    "options": ["Bern", "Zurich", "Geneva", "Basel"],
    "answer": "Bern"
  },
  {
    "question": "Which is the largest living salamander?",
    "options": ["Chinese Giant Salamander", "Axolotl", "Tiger Salamander", "Fire Salamander"],
    "answer": "Chinese Giant Salamander"
  },
  {
    "question": "What is the main ingredient in pesto?",
    "options": ["Basil", "Parsley", "Cilantro", "Mint"],
    "answer": "Basil"
  },
  {
    "question": "Which is the largest living bear?",
    "options": ["Polar Bear", "Grizzly Bear", "Kodiak Bear", "Black Bear"],
    "answer": "Kodiak Bear"
  },
  {
    "question": "What is the capital of Austria?",
    "options": ["Vienna", "Salzburg", "Graz", "Innsbruck"],
    "answer": "Vienna"
  },
  {
    "question": "Which is the largest living rodent in Africa?",
    "options": ["Porcupine", "Gambian Pouched Rat", "Naked Mole Rat", "Springhare"],
    "answer": "Porcupine"
  },
  {
    "question": "What is the main ingredient in sauerkraut?",
    "options": ["Cabbage", "Carrot", "Radish", "Turnip"],
    "answer": "Cabbage"
  },
  {
    "question": "Which is the largest living marsupial in the Americas?",
    "options": ["Opossum", "Kangaroo", "Koala", "Wombat"],
    "answer": "Opossum"
  },
  {
    "question": "What is the capital of Belgium?",
    "options": ["Brussels", "Antwerp", "Ghent", "Bruges"],
    "answer": "Brussels"
  },
  {
    "question": "Which is the largest living rodent in Europe?",
    "options": ["Beaver", "Muskrat", "Porcupine", "Mole"],
    "answer": "Beaver"
  },
  {
    "question": "What is the main ingredient in tzatziki?",
    "options": ["Yogurt", "Sour Cream", "Mayonnaise", "Cream Cheese"],
    "answer": "Yogurt"
  },
  {
    "question": "Which is the largest living rodent in Asia?",
    "options": ["Capybara", "Giant Squirrel", "Beaver", "Porcupine"],
    "answer": "Porcupine"
  },
  {
    "question": "What is the capital of the Netherlands?",
    "options": ["Amsterdam", "Rotterdam", "The Hague", "Utrecht"],
    "answer": "Amsterdam"
  },
  {
    "question": "Which is the largest living rodent in Australia?",
    "options": ["Water Rat", "Bush Rat", "Swamp Rat", "Long-haired Rat"],
    "answer": "Water Rat"
  },
  {
    "question": "What is the main ingredient in bolognese sauce?",
    "options": ["Beef", "Pork", "Chicken", "Lamb"],
    "answer": "Beef"
  },
  {
    "question": "Which is the largest living rodent in Antarctica?",
    "options": ["None", "Seal", "Penguin", "Skua"],
    "answer": "None"
  },
  {
    "question": "What is the capital of New Zealand?",
    "options": ["Wellington", "Auckland", "Christchurch", "Dunedin"],
    "answer": "Wellington"
  },
  {
    "question": "Which is the largest living rodent in South America?",
    "options": ["Capybara", "Guinea Pig", "Chinchilla", "Agouti"],
    "answer": "Capybara"
  },
  {
    "question": "What is the main ingredient in sushi rolls?",
    "options": ["Rice", "Seaweed", "Fish", "Vegetables"],
    "answer": "Rice"
  }
]
